{
    "web": {
        "client_id": "847737198899-1ffuivfgnsjsv4klhj4foui4ehclfsl5.apps.googleusercontent.com",
        "project_id": "sandbox-io-289003",
        "auth_uri": "https://accounts.google.com/o/oauth2/auth",
        "token_uri": "https://oauth2.googleapis.com/token",
        "auth_provider_x509_cert_url": "https://www.googleapis.com/oauth2/v1/certs",
        "client_secret": "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",
        "redirect_uris": [
            "http://127.0.0.1:8080/oauth2callback"
        ],
        "javascript_origins": [
            "https://8080-cs-4e15b47e-3a90-4abe-a89c-2da3fa2201b7.cs-asia-southeast1-yelo.cloudshell.dev"
        ]
    }
}